{
    "id": 132,
    "children": [
        {
            "type": 6,
            "id": 0,
            "format": 1,
            "menuType": 0,
            "contentType": 0,
            "originalX": 212,
            "originalY": 75,
            "width": 55,
            "height": 81,
            "opacity": 0,
            "parentId": -1,
            "hoveredSiblingId": -1,
            "x": 212,
            "y": 75,
            "modelType": 1,
            "alternateModelType": 1,
            "modelId": 7120,
            "alternateModelId": -1,
            "animation": -1,
            "alternateAnimation": -1,
            "modelZoom": 671,
            "rotationX": 510,
            "rotationY": 0
        },
        {
            "type": 4,
            "id": 1,
            "format": 1,
            "menuType": 0,
            "contentType": 0,
            "originalX": 61,
            "originalY": 68,
            "width": 331,
            "height": 14,
            "opacity": 0,
            "parentId": -1,
            "hoveredSiblingId": -1,
            "x": 61,
            "y": 68,
            "textAlignmentX": 1,
            "textAlignmentY": 0,
            "lineHeight": 0,
            "fontId": 495,
            "textShadowed": false,
            "text": "lj1",
            "alternateText": "",
            "textColor": 0,
            "alternateTextColor": 0,
            "hoveredTextColor": 0,
            "alternateHoveredTextColor": 0
        },
        {
            "type": 4,
            "id": 2,
            "format": 1,
            "menuType": 0,
            "contentType": 0,
            "originalX": 61,
            "originalY": 84,
            "width": 331,
            "height": 14,
            "opacity": 0,
            "parentId": -1,
            "hoveredSiblingId": -1,
            "x": 61,
            "y": 84,
            "textAlignmentX": 1,
            "textAlignmentY": 0,
            "lineHeight": 0,
            "fontId": 495,
            "textShadowed": false,
            "text": "lj2",
            "alternateText": "",
            "textColor": 0,
            "alternateTextColor": 0,
            "hoveredTextColor": 0,
            "alternateHoveredTextColor": 0
        },
        {
            "type": 4,
            "id": 3,
            "format": 1,
            "menuType": 0,
            "contentType": 0,
            "originalX": 61,
            "originalY": 100,
            "width": 331,
            "height": 14,
            "opacity": 0,
            "parentId": -1,
            "hoveredSiblingId": -1,
            "x": 61,
            "y": 100,
            "textAlignmentX": 1,
            "textAlignmentY": 0,
            "lineHeight": 0,
            "fontId": 495,
            "textShadowed": false,
            "text": "lj3",
            "alternateText": "",
            "textColor": 0,
            "alternateTextColor": 0,
            "hoveredTextColor": 0,
            "alternateHoveredTextColor": 0
        },
        {
            "type": 4,
            "id": 4,
            "format": 1,
            "menuType": 0,
            "contentType": 0,
            "originalX": 61,
            "originalY": 116,
            "width": 331,
            "height": 14,
            "opacity": 0,
            "parentId": -1,
            "hoveredSiblingId": -1,
            "x": 61,
            "y": 116,
            "textAlignmentX": 1,
            "textAlignmentY": 0,
            "lineHeight": 0,
            "fontId": 495,
            "textShadowed": false,
            "text": "lj4",
            "alternateText": "",
            "textColor": 0,
            "alternateTextColor": 0,
            "hoveredTextColor": 0,
            "alternateHoveredTextColor": 0
        },
        {
            "type": 4,
            "id": 5,
            "format": 1,
            "menuType": 0,
            "contentType": 0,
            "originalX": 61,
            "originalY": 132,
            "width": 331,
            "height": 14,
            "opacity": 0,
            "parentId": -1,
            "hoveredSiblingId": -1,
            "x": 61,
            "y": 132,
            "textAlignmentX": 1,
            "textAlignmentY": 0,
            "lineHeight": 0,
            "fontId": 495,
            "textShadowed": false,
            "text": "lj5",
            "alternateText": "",
            "textColor": 0,
            "alternateTextColor": 0,
            "hoveredTextColor": 0,
            "alternateHoveredTextColor": 0
        },
        {
            "type": 4,
            "id": 6,
            "format": 1,
            "menuType": 0,
            "contentType": 0,
            "originalX": 61,
            "originalY": 148,
            "width": 331,
            "height": 14,
            "opacity": 0,
            "parentId": -1,
            "hoveredSiblingId": -1,
            "x": 61,
            "y": 148,
            "textAlignmentX": 1,
            "textAlignmentY": 0,
            "lineHeight": 0,
            "fontId": 495,
            "textShadowed": false,
            "text": "lj6",
            "alternateText": "",
            "textColor": 0,
            "alternateTextColor": 0,
            "hoveredTextColor": 0,
            "alternateHoveredTextColor": 0
        },
        {
            "type": 4,
            "id": 7,
            "format": 1,
            "menuType": 0,
            "contentType": 0,
            "originalX": 61,
            "originalY": 164,
            "width": 331,
            "height": 14,
            "opacity": 0,
            "parentId": -1,
            "hoveredSiblingId": -1,
            "x": 61,
            "y": 164,
            "textAlignmentX": 1,
            "textAlignmentY": 0,
            "lineHeight": 0,
            "fontId": 495,
            "textShadowed": false,
            "text": "lj7",
            "alternateText": "",
            "textColor": 0,
            "alternateTextColor": 0,
            "hoveredTextColor": 0,
            "alternateHoveredTextColor": 0
        },
        {
            "type": 4,
            "id": 8,
            "format": 1,
            "menuType": 0,
            "contentType": 0,
            "originalX": 61,
            "originalY": 180,
            "width": 331,
            "height": 14,
            "opacity": 0,
            "parentId": -1,
            "hoveredSiblingId": -1,
            "x": 61,
            "y": 180,
            "textAlignmentX": 1,
            "textAlignmentY": 0,
            "lineHeight": 0,
            "fontId": 495,
            "textShadowed": false,
            "text": "lj8",
            "alternateText": "",
            "textColor": 0,
            "alternateTextColor": 0,
            "hoveredTextColor": 0,
            "alternateHoveredTextColor": 0
        },
        {
            "type": 4,
            "id": 9,
            "format": 1,
            "menuType": 0,
            "contentType": 0,
            "originalX": 61,
            "originalY": 196,
            "width": 331,
            "height": 14,
            "opacity": 0,
            "parentId": -1,
            "hoveredSiblingId": -1,
            "x": 61,
            "y": 196,
            "textAlignmentX": 1,
            "textAlignmentY": 0,
            "lineHeight": 0,
            "fontId": 495,
            "textShadowed": false,
            "text": "lj9",
            "alternateText": "",
            "textColor": 0,
            "alternateTextColor": 0,
            "hoveredTextColor": 0,
            "alternateHoveredTextColor": 0
        },
        {
            "type": 4,
            "id": 10,
            "format": 1,
            "menuType": 0,
            "contentType": 0,
            "originalX": 61,
            "originalY": 212,
            "width": 331,
            "height": 14,
            "opacity": 0,
            "parentId": -1,
            "hoveredSiblingId": -1,
            "x": 61,
            "y": 212,
            "textAlignmentX": 1,
            "textAlignmentY": 0,
            "lineHeight": 0,
            "fontId": 495,
            "textShadowed": false,
            "text": "lj10",
            "alternateText": "",
            "textColor": 0,
            "alternateTextColor": 0,
            "hoveredTextColor": 0,
            "alternateHoveredTextColor": 0
        },
        {
            "type": 4,
            "id": 11,
            "format": 1,
            "menuType": 0,
            "contentType": 0,
            "originalX": 61,
            "originalY": 228,
            "width": 331,
            "height": 14,
            "opacity": 0,
            "parentId": -1,
            "hoveredSiblingId": -1,
            "x": 61,
            "y": 228,
            "textAlignmentX": 1,
            "textAlignmentY": 0,
            "lineHeight": 0,
            "fontId": 495,
            "textShadowed": false,
            "text": "lj11",
            "alternateText": "",
            "textColor": 0,
            "alternateTextColor": 0,
            "hoveredTextColor": 0,
            "alternateHoveredTextColor": 0
        },
        {
            "type": 0,
            "id": 12,
            "format": 1,
            "menuType": 0,
            "contentType": 0,
            "originalX": 58,
            "originalY": 63,
            "width": 340,
            "height": 23,
            "opacity": 0,
            "parentId": -1,
            "hoveredSiblingId": -1,
            "x": 58,
            "y": 63,
            "scrollHeight": 0,
            "hidden": false
        },
        {
            "type": 4,
            "id": 13,
            "format": 1,
            "menuType": 0,
            "contentType": 0,
            "originalX": 12,
            "originalY": 5,
            "width": 18,
            "height": 14,
            "opacity": 0,
            "parentId": 12,
            "hoveredSiblingId": -1,
            "x": 12,
            "y": 5,
            "textAlignmentX": 1,
            "textAlignmentY": 0,
            "lineHeight": 0,
            "fontId": 495,
            "textShadowed": true,
            "text": ">>>",
            "alternateText": "",
            "textColor": 16711680,
            "alternateTextColor": 0,
            "hoveredTextColor": 0,
            "alternateHoveredTextColor": 0
        },
        {
            "type": 4,
            "id": 14,
            "format": 1,
            "menuType": 0,
            "contentType": 0,
            "originalX": 306,
            "originalY": 5,
            "width": 18,
            "height": 14,
            "opacity": 0,
            "parentId": 12,
            "hoveredSiblingId": -1,
            "x": 306,
            "y": 5,
            "textAlignmentX": 1,
            "textAlignmentY": 0,
            "lineHeight": 0,
            "fontId": 495,
            "textShadowed": true,
            "text": "<<<",
            "alternateText": "",
            "textColor": 16711680,
            "alternateTextColor": 0,
            "hoveredTextColor": 0,
            "alternateHoveredTextColor": 0
        },
        {
            "type": 0,
            "id": 15,
            "format": 1,
            "menuType": 0,
            "contentType": 0,
            "originalX": 58,
            "originalY": 79,
            "width": 340,
            "height": 23,
            "opacity": 0,
            "parentId": -1,
            "hoveredSiblingId": -1,
            "x": 58,
            "y": 79,
            "scrollHeight": 0,
            "hidden": false
        },
        {
            "type": 4,
            "id": 16,
            "format": 1,
            "menuType": 0,
            "contentType": 0,
            "originalX": 12,
            "originalY": 5,
            "width": 18,
            "height": 14,
            "opacity": 0,
            "parentId": 15,
            "hoveredSiblingId": -1,
            "x": 12,
            "y": 5,
            "textAlignmentX": 1,
            "textAlignmentY": 0,
            "lineHeight": 0,
            "fontId": 495,
            "textShadowed": true,
            "text": ">>>",
            "alternateText": "",
            "textColor": 16711680,
            "alternateTextColor": 0,
            "hoveredTextColor": 0,
            "alternateHoveredTextColor": 0
        },
        {
            "type": 4,
            "id": 17,
            "format": 1,
            "menuType": 0,
            "contentType": 0,
            "originalX": 306,
            "originalY": 5,
            "width": 18,
            "height": 14,
            "opacity": 0,
            "parentId": 15,
            "hoveredSiblingId": -1,
            "x": 306,
            "y": 5,
            "textAlignmentX": 1,
            "textAlignmentY": 0,
            "lineHeight": 0,
            "fontId": 495,
            "textShadowed": true,
            "text": "<<<",
            "alternateText": "",
            "textColor": 16711680,
            "alternateTextColor": 0,
            "hoveredTextColor": 0,
            "alternateHoveredTextColor": 0
        },
        {
            "type": 0,
            "id": 18,
            "format": 1,
            "menuType": 0,
            "contentType": 0,
            "originalX": 58,
            "originalY": 95,
            "width": 340,
            "height": 23,
            "opacity": 0,
            "parentId": -1,
            "hoveredSiblingId": -1,
            "x": 58,
            "y": 95,
            "scrollHeight": 0,
            "hidden": false
        },
        {
            "type": 4,
            "id": 19,
            "format": 1,
            "menuType": 0,
            "contentType": 0,
            "originalX": 12,
            "originalY": 5,
            "width": 18,
            "height": 14,
            "opacity": 0,
            "parentId": 18,
            "hoveredSiblingId": -1,
            "x": 12,
            "y": 5,
            "textAlignmentX": 1,
            "textAlignmentY": 0,
            "lineHeight": 0,
            "fontId": 495,
            "textShadowed": true,
            "text": ">>>",
            "alternateText": "",
            "textColor": 16711680,
            "alternateTextColor": 0,
            "hoveredTextColor": 0,
            "alternateHoveredTextColor": 0
        },
        {
            "type": 4,
            "id": 20,
            "format": 1,
            "menuType": 0,
            "contentType": 0,
            "originalX": 306,
            "originalY": 5,
            "width": 18,
            "height": 14,
            "opacity": 0,
            "parentId": 18,
            "hoveredSiblingId": -1,
            "x": 306,
            "y": 5,
            "textAlignmentX": 1,
            "textAlignmentY": 0,
            "lineHeight": 0,
            "fontId": 495,
            "textShadowed": true,
            "text": "<<<",
            "alternateText": "",
            "textColor": 16711680,
            "alternateTextColor": 0,
            "hoveredTextColor": 0,
            "alternateHoveredTextColor": 0
        },
        {
            "type": 0,
            "id": 21,
            "format": 1,
            "menuType": 0,
            "contentType": 0,
            "originalX": 58,
            "originalY": 111,
            "width": 340,
            "height": 23,
            "opacity": 0,
            "parentId": -1,
            "hoveredSiblingId": -1,
            "x": 58,
            "y": 111,
            "scrollHeight": 0,
            "hidden": false
        },
        {
            "type": 4,
            "id": 22,
            "format": 1,
            "menuType": 0,
            "contentType": 0,
            "originalX": 12,
            "originalY": 5,
            "width": 18,
            "height": 14,
            "opacity": 0,
            "parentId": 21,
            "hoveredSiblingId": -1,
            "x": 12,
            "y": 5,
            "textAlignmentX": 1,
            "textAlignmentY": 0,
            "lineHeight": 0,
            "fontId": 495,
            "textShadowed": true,
            "text": ">>>",
            "alternateText": "",
            "textColor": 16711680,
            "alternateTextColor": 0,
            "hoveredTextColor": 0,
            "alternateHoveredTextColor": 0
        },
        {
            "type": 4,
            "id": 23,
            "format": 1,
            "menuType": 0,
            "contentType": 0,
            "originalX": 306,
            "originalY": 5,
            "width": 18,
            "height": 14,
            "opacity": 0,
            "parentId": 21,
            "hoveredSiblingId": -1,
            "x": 306,
            "y": 5,
            "textAlignmentX": 1,
            "textAlignmentY": 0,
            "lineHeight": 0,
            "fontId": 495,
            "textShadowed": true,
            "text": "<<<",
            "alternateText": "",
            "textColor": 16711680,
            "alternateTextColor": 0,
            "hoveredTextColor": 0,
            "alternateHoveredTextColor": 0
        },
        {
            "type": 0,
            "id": 24,
            "format": 1,
            "menuType": 0,
            "contentType": 0,
            "originalX": 58,
            "originalY": 127,
            "width": 340,
            "height": 23,
            "opacity": 0,
            "parentId": -1,
            "hoveredSiblingId": -1,
            "x": 58,
            "y": 127,
            "scrollHeight": 0,
            "hidden": false
        },
        {
            "type": 4,
            "id": 25,
            "format": 1,
            "menuType": 0,
            "contentType": 0,
            "originalX": 12,
            "originalY": 5,
            "width": 18,
            "height": 14,
            "opacity": 0,
            "parentId": 24,
            "hoveredSiblingId": -1,
            "x": 12,
            "y": 5,
            "textAlignmentX": 1,
            "textAlignmentY": 0,
            "lineHeight": 0,
            "fontId": 495,
            "textShadowed": true,
            "text": ">>>",
            "alternateText": "",
            "textColor": 16711680,
            "alternateTextColor": 0,
            "hoveredTextColor": 0,
            "alternateHoveredTextColor": 0
        },
        {
            "type": 4,
            "id": 26,
            "format": 1,
            "menuType": 0,
            "contentType": 0,
            "originalX": 306,
            "originalY": 5,
            "width": 18,
            "height": 14,
            "opacity": 0,
            "parentId": 24,
            "hoveredSiblingId": -1,
            "x": 306,
            "y": 5,
            "textAlignmentX": 1,
            "textAlignmentY": 0,
            "lineHeight": 0,
            "fontId": 495,
            "textShadowed": true,
            "text": "<<<",
            "alternateText": "",
            "textColor": 16711680,
            "alternateTextColor": 0,
            "hoveredTextColor": 0,
            "alternateHoveredTextColor": 0
        },
        {
            "type": 0,
            "id": 27,
            "format": 1,
            "menuType": 0,
            "contentType": 0,
            "originalX": 58,
            "originalY": 143,
            "width": 340,
            "height": 23,
            "opacity": 0,
            "parentId": -1,
            "hoveredSiblingId": -1,
            "x": 58,
            "y": 143,
            "scrollHeight": 0,
            "hidden": false
        },
        {
            "type": 4,
            "id": 28,
            "format": 1,
            "menuType": 0,
            "contentType": 0,
            "originalX": 12,
            "originalY": 5,
            "width": 18,
            "height": 14,
            "opacity": 0,
            "parentId": 27,
            "hoveredSiblingId": -1,
            "x": 12,
            "y": 5,
            "textAlignmentX": 1,
            "textAlignmentY": 0,
            "lineHeight": 0,
            "fontId": 495,
            "textShadowed": true,
            "text": ">>>",
            "alternateText": "",
            "textColor": 16711680,
            "alternateTextColor": 0,
            "hoveredTextColor": 0,
            "alternateHoveredTextColor": 0
        },
        {
            "type": 4,
            "id": 29,
            "format": 1,
            "menuType": 0,
            "contentType": 0,
            "originalX": 306,
            "originalY": 5,
            "width": 18,
            "height": 14,
            "opacity": 0,
            "parentId": 27,
            "hoveredSiblingId": -1,
            "x": 306,
            "y": 5,
            "textAlignmentX": 1,
            "textAlignmentY": 0,
            "lineHeight": 0,
            "fontId": 495,
            "textShadowed": true,
            "text": "<<<",
            "alternateText": "",
            "textColor": 16711680,
            "alternateTextColor": 0,
            "hoveredTextColor": 0,
            "alternateHoveredTextColor": 0
        },
        {
            "type": 0,
            "id": 30,
            "format": 1,
            "menuType": 0,
            "contentType": 0,
            "originalX": 58,
            "originalY": 159,
            "width": 340,
            "height": 23,
            "opacity": 0,
            "parentId": -1,
            "hoveredSiblingId": -1,
            "x": 58,
            "y": 159,
            "scrollHeight": 0,
            "hidden": false
        },
        {
            "type": 4,
            "id": 31,
            "format": 1,
            "menuType": 0,
            "contentType": 0,
            "originalX": 12,
            "originalY": 5,
            "width": 18,
            "height": 14,
            "opacity": 0,
            "parentId": 30,
            "hoveredSiblingId": -1,
            "x": 12,
            "y": 5,
            "textAlignmentX": 1,
            "textAlignmentY": 0,
            "lineHeight": 0,
            "fontId": 495,
            "textShadowed": true,
            "text": ">>>",
            "alternateText": "",
            "textColor": 16711680,
            "alternateTextColor": 0,
            "hoveredTextColor": 0,
            "alternateHoveredTextColor": 0
        },
        {
            "type": 4,
            "id": 32,
            "format": 1,
            "menuType": 0,
            "contentType": 0,
            "originalX": 306,
            "originalY": 5,
            "width": 18,
            "height": 14,
            "opacity": 0,
            "parentId": 30,
            "hoveredSiblingId": -1,
            "x": 306,
            "y": 5,
            "textAlignmentX": 1,
            "textAlignmentY": 0,
            "lineHeight": 0,
            "fontId": 495,
            "textShadowed": true,
            "text": "<<<",
            "alternateText": "",
            "textColor": 16711680,
            "alternateTextColor": 0,
            "hoveredTextColor": 0,
            "alternateHoveredTextColor": 0
        },
        {
            "type": 0,
            "id": 33,
            "format": 1,
            "menuType": 0,
            "contentType": 0,
            "originalX": 58,
            "originalY": 175,
            "width": 340,
            "height": 23,
            "opacity": 0,
            "parentId": -1,
            "hoveredSiblingId": -1,
            "x": 58,
            "y": 175,
            "scrollHeight": 0,
            "hidden": false
        },
        {
            "type": 4,
            "id": 34,
            "format": 1,
            "menuType": 0,
            "contentType": 0,
            "originalX": 12,
            "originalY": 5,
            "width": 18,
            "height": 14,
            "opacity": 0,
            "parentId": 33,
            "hoveredSiblingId": -1,
            "x": 12,
            "y": 5,
            "textAlignmentX": 1,
            "textAlignmentY": 0,
            "lineHeight": 0,
            "fontId": 495,
            "textShadowed": true,
            "text": ">>>",
            "alternateText": "",
            "textColor": 16711680,
            "alternateTextColor": 0,
            "hoveredTextColor": 0,
            "alternateHoveredTextColor": 0
        },
        {
            "type": 4,
            "id": 35,
            "format": 1,
            "menuType": 0,
            "contentType": 0,
            "originalX": 306,
            "originalY": 5,
            "width": 18,
            "height": 14,
            "opacity": 0,
            "parentId": 33,
            "hoveredSiblingId": -1,
            "x": 306,
            "y": 5,
            "textAlignmentX": 1,
            "textAlignmentY": 0,
            "lineHeight": 0,
            "fontId": 495,
            "textShadowed": true,
            "text": "<<<",
            "alternateText": "",
            "textColor": 16711680,
            "alternateTextColor": 0,
            "hoveredTextColor": 0,
            "alternateHoveredTextColor": 0
        },
        {
            "type": 0,
            "id": 36,
            "format": 1,
            "menuType": 0,
            "contentType": 0,
            "originalX": 58,
            "originalY": 191,
            "width": 340,
            "height": 23,
            "opacity": 0,
            "parentId": -1,
            "hoveredSiblingId": -1,
            "x": 58,
            "y": 191,
            "scrollHeight": 0,
            "hidden": false
        },
        {
            "type": 4,
            "id": 37,
            "format": 1,
            "menuType": 0,
            "contentType": 0,
            "originalX": 12,
            "originalY": 5,
            "width": 18,
            "height": 14,
            "opacity": 0,
            "parentId": 36,
            "hoveredSiblingId": -1,
            "x": 12,
            "y": 5,
            "textAlignmentX": 1,
            "textAlignmentY": 0,
            "lineHeight": 0,
            "fontId": 495,
            "textShadowed": true,
            "text": ">>>",
            "alternateText": "",
            "textColor": 16711680,
            "alternateTextColor": 0,
            "hoveredTextColor": 0,
            "alternateHoveredTextColor": 0
        },
        {
            "type": 4,
            "id": 38,
            "format": 1,
            "menuType": 0,
            "contentType": 0,
            "originalX": 306,
            "originalY": 5,
            "width": 18,
            "height": 14,
            "opacity": 0,
            "parentId": 36,
            "hoveredSiblingId": -1,
            "x": 306,
            "y": 5,
            "textAlignmentX": 1,
            "textAlignmentY": 0,
            "lineHeight": 0,
            "fontId": 495,
            "textShadowed": true,
            "text": "<<<",
            "alternateText": "",
            "textColor": 16711680,
            "alternateTextColor": 0,
            "hoveredTextColor": 0,
            "alternateHoveredTextColor": 0
        },
        {
            "type": 0,
            "id": 39,
            "format": 1,
            "menuType": 0,
            "contentType": 0,
            "originalX": 58,
            "originalY": 207,
            "width": 340,
            "height": 23,
            "opacity": 0,
            "parentId": -1,
            "hoveredSiblingId": -1,
            "x": 58,
            "y": 207,
            "scrollHeight": 0,
            "hidden": false
        },
        {
            "type": 4,
            "id": 40,
            "format": 1,
            "menuType": 0,
            "contentType": 0,
            "originalX": 12,
            "originalY": 5,
            "width": 18,
            "height": 14,
            "opacity": 0,
            "parentId": 39,
            "hoveredSiblingId": -1,
            "x": 12,
            "y": 5,
            "textAlignmentX": 1,
            "textAlignmentY": 0,
            "lineHeight": 0,
            "fontId": 495,
            "textShadowed": true,
            "text": ">>>",
            "alternateText": "",
            "textColor": 16711680,
            "alternateTextColor": 0,
            "hoveredTextColor": 0,
            "alternateHoveredTextColor": 0
        },
        {
            "type": 4,
            "id": 41,
            "format": 1,
            "menuType": 0,
            "contentType": 0,
            "originalX": 306,
            "originalY": 5,
            "width": 18,
            "height": 14,
            "opacity": 0,
            "parentId": 39,
            "hoveredSiblingId": -1,
            "x": 306,
            "y": 5,
            "textAlignmentX": 1,
            "textAlignmentY": 0,
            "lineHeight": 0,
            "fontId": 495,
            "textShadowed": true,
            "text": "<<<",
            "alternateText": "",
            "textColor": 16711680,
            "alternateTextColor": 0,
            "hoveredTextColor": 0,
            "alternateHoveredTextColor": 0
        },
        {
            "type": 0,
            "id": 42,
            "format": 1,
            "menuType": 0,
            "contentType": 0,
            "originalX": 58,
            "originalY": 223,
            "width": 340,
            "height": 23,
            "opacity": 0,
            "parentId": -1,
            "hoveredSiblingId": -1,
            "x": 58,
            "y": 223,
            "scrollHeight": 0,
            "hidden": false
        },
        {
            "type": 4,
            "id": 43,
            "format": 1,
            "menuType": 0,
            "contentType": 0,
            "originalX": 12,
            "originalY": 5,
            "width": 18,
            "height": 14,
            "opacity": 0,
            "parentId": 42,
            "hoveredSiblingId": -1,
            "x": 12,
            "y": 5,
            "textAlignmentX": 1,
            "textAlignmentY": 0,
            "lineHeight": 0,
            "fontId": 495,
            "textShadowed": true,
            "text": ">>>",
            "alternateText": "",
            "textColor": 16711680,
            "alternateTextColor": 0,
            "hoveredTextColor": 0,
            "alternateHoveredTextColor": 0
        },
        {
            "type": 4,
            "id": 44,
            "format": 1,
            "menuType": 0,
            "contentType": 0,
            "originalX": 306,
            "originalY": 5,
            "width": 18,
            "height": 14,
            "opacity": 0,
            "parentId": 42,
            "hoveredSiblingId": -1,
            "x": 306,
            "y": 5,
            "textAlignmentX": 1,
            "textAlignmentY": 0,
            "lineHeight": 0,
            "fontId": 495,
            "textShadowed": true,
            "text": "<<<",
            "alternateText": "",
            "textColor": 16711680,
            "alternateTextColor": 0,
            "hoveredTextColor": 0,
            "alternateHoveredTextColor": 0
        },
        {
            "type": 4,
            "id": 45,
            "format": 1,
            "menuType": 0,
            "contentType": 0,
            "originalX": 60,
            "originalY": 27,
            "width": 299,
            "height": 36,
            "opacity": 0,
            "parentId": -1,
            "hoveredSiblingId": -1,
            "x": 60,
            "y": 27,
            "textAlignmentX": 1,
            "textAlignmentY": 1,
            "lineHeight": 0,
            "fontId": 495,
            "textShadowed": true,
            "text": "Items I need to get for King Roald's garden:",
            "alternateText": "",
            "textColor": 14132595,
            "alternateTextColor": 0,
            "hoveredTextColor": 0,
            "alternateHoveredTextColor": 0
        },
        {
            "type": 5,
            "id": 46,
            "format": 1,
            "menuType": 0,
            "contentType": 0,
            "originalX": 362,
            "originalY": 30,
            "width": 23,
            "height": 23,
            "opacity": 0,
            "parentId": -1,
            "hoveredSiblingId": 48,
            "x": 362,
            "y": 30,
            "spriteId": 537,
            "alternateSpriteId": -1
        },
        {
            "type": 5,
            "id": 47,
            "format": 1,
            "menuType": 3,
            "contentType": 0,
            "originalX": 5,
            "originalY": 5,
            "width": 23,
            "height": 23,
            "opacity": 0,
            "parentId": 48,
            "hoveredSiblingId": -1,
            "x": 5,
            "y": 5,
            "spriteId": 538,
            "alternateSpriteId": -1
        },
        {
            "type": 0,
            "id": 48,
            "format": 1,
            "menuType": 0,
            "contentType": 0,
            "originalX": 357,
            "originalY": 25,
            "width": 32,
            "height": 32,
            "opacity": 0,
            "parentId": -1,
            "hoveredSiblingId": -1,
            "x": 357,
            "y": 25,
            "scrollHeight": 0,
            "hidden": true
        }
    ]
}